{
  "2D":{
    "pzmu_ptmu":{"name":"pzmu_ptmu",
                 "xvar":"pzmu",
                 "yvar":"ptmu"},
    "EnuCCQE_Q2QE":{"name":"EnuCCQE_Q2QE",
                    "xvar":"EnuCCQE",
                    "yvar":"Q2QE"},
    "Q2QE_recoil":{"name":"Q2QE_recoil",
                   "xvar":"Q2QE",
                   "yvar":"recoil"},
    "EnuCCQE_ThetamuDegrees":{"name":"EnuCCQE_ThetamuDegrees",
                              "xvar":"EnuCCQE",
                              "yvar":"ThetamuDegrees"},
    "pmu_ThetamuDegrees":{"name":"pmu_ThetamuDegrees",
                          "xvar":"pmu",
                          "yvar":"ThetamuDegrees"},
    "nMichel_nImprovedMichel":{"name":"nMichel_nImprovedMichel",
                               "xvar":"MichelCount",
                               "yvar":"ImprovedMichelCount"},
    "nMichel_nFittedMichel":{"name":"nMichel_nFittedMichel",
                               "xvar":"MichelCount",
                               "yvar":"FittedMichelCount"},
    "nImprovedMichel_nFittedMichel":{"name":"nImprovedMichel_nFittedMichel",
                               "xvar":"ImprovedMichelCount",
                               "yvar":"FittedMichelCount"},
    "nBlob_nImprovedMichel":{"name":"nBlob_nImprovedMichel",
                             "xvar":"BlobCount",
                             "yvar":"ImprovedMichelCount"},
    "nBlob_nMichel":{"name":"nBlob_nMichel",
                     "xvar":"BlobCount",
                     "yvar":"MichelCount"},
    "ProtonCount_Q2QEsimplebin":{"name":"ProtonCount_Q2QE",
                                 "xvar":"ProtonCount",
                                 "yvar":"Q2QEsimplebin"},
    "PrimaryProtonScore_Q2QEsimplebin":{"name":"PrimaryProtonScore_Q2QE",
                                        "xvar":"PrimaryProtonScore",
                                        "yvar":"Q2QEsimplebin"}
  },
  "1D":{
    "EnuCCQE":{"reco":"EnuCCQEGeV",
               "true":"TrueEnuCCQEGeV",
               "name":"EnuCCQE",
               "title":"Reconstructed E_{#nu}_{QE} (GeV)",
               "units":"GeV",
               "bins":[2.0, 2.5, 3.0, 3.5, 4.0, 4.5, 5.0, 6.0, 7.0, 8.0, 9.0, 10.0, 15.0],
               "fluxnorm":1},
    "Enu":{"reco":"EnuCCQEGeV",
           "true":"TrueEnuGeV",
           "name":"Enu",
           "title":"Reconstructed E_{#nu} (GeV)",
           "units":"GeV",
           "bins":[2.0, 2.5, 3.0, 3.5, 4.0, 4.5, 5.0, 6.0, 7.0, 8.0, 9.0, 10.0, 15.0],
           "fluxnorm":1},
    "EnuHad":{"reco":"EnuHadGeV",
              "true":"TrueEnuGeV",
              "name":"EnuHad",
              "title":"Reconstructed E_{#nu}_{hadronic} (GeV)",
              "units":"GeV",
              "bins":[2.0, 2.5, 3.0, 3.5, 4.0, 4.5, 5.0, 6.0, 7.0, 8.0, 9.0, 10.0, 15.0],
              "fluxnorm":1},
    "total":{"reco":"EnuCCQEGeV",
             "true":"TrueEnuCCQEGeV",
             "name":"total",
             "title":"total Reconstructed E_{#nu} from 2 to 15 GeV (GeV)",
             "units":"GeV",
             "bins":[2.0,15.0],
             "fluxnorm":0},
    "ptmu":{"reco":"PperpMuGeV",
            "true":"TruePperpMuGeV",
            "name":"ptmu",
            "title":"Reconstructed Muon p_{T} (GeV)",
            "units":"GeV",
            "bins":[0.0,0.075,0.15,0.25,0.325,0.4,0.475,0.55,0.7,0.85,1,1.25,1.5,2.5],
            "fluxnorm":false},
    "pzmu":{"reco":"PparMuGeV",
            "true":"TruePparMuGeV",
            "name":"pzmu",
            "title":"Reconstructed Muon p_{||} (GeV)",
            "units":"GeV",
            "bins":[0., 1., 2. , 3. , 4. , 5. , 6. , 7. , 8. , 9. , 10. , 15. ],
            "fluxnorm":false},
    "pmu":{"reco":"PmuGeV",
           "true":"TruePmuGeV",
           "name":"pmu",
           "title":"Reconstructed Muon p (GeV)",
           "units":"GeV",
           "bins":[0., 0.5, 1., 1.5, 2. , 3. , 4. , 5. , 6. , 7. , 8. , 9. , 10. , 15. ],
           "fluxnorm":false},
    "Q2QE":{"reco":"Q2QEGeV",
            "true":"TrueQ2QEGeV",
            "name":"Q2QE",
            "title":"Reconstructed QE Q^{2} (GeV^{2})",
            "units":"GeV^{2}",
            "bins":[0.001, 0.00625, 0.0125, 0.025, 0.0375, 0.05, 0.10, 0.20, 0.30, 0.40, 0.60, 0.80, 1.0, 1.2, 2.0],
            "fluxnorm":false},
    "Q2QEsimplebin":{"reco":"Q2QEGeV",
                     "true":"TrueQ2QEGeV",
                     "name":"Q2QE",
                     "title":"Reconstructed QE Q^{2} (GeV^{2})",
                     "units":"GeV^{2}",
                     "bins":[0.0,0.03, 0.05, 0.10, 0.20, 0.40, 0.60, 0.80, 1.0, 1.2, 2.0, 3.0, 4.0],
                     "fluxnorm":false},
    "zmax":{"reco":"ZVertex",
            "true":"TrueZVertex",
            "name":"zmax",
            "title":"z near end",
            "nbins":100,
            "min":8300.,
            "max":8500.,
            "fluxnorm":false},
    "zmin":{"reco":"ZVertex",
            "true":"TrueZVertex",
            "name":"zmin",
            "title":"z near start",
            "nbins":100,
            "min":5700.,
            "max":5900.,
            "fluxnorm":false},
    "curv":{"reco":"Curvature",
            "true":"TrueCurvature",
            "name":"curv",
            "title":"curvature in MINOS, m-1",
            "nbins":100,
            "min":-2.,
            "max":2.,
            "for":["data","selected_reco"],
            "fluxnorm":false},
    "recoil":{"reco":"RecoilEnergyGeV",
              "true":"TrueRecoilEnergyGeV",
              "name":"recoil",
              "title":"Reconstructed Recoil (GeV)",
              "units":"GeV",
              "nbins":25,
              "min":0.0,
              "max":0.5,
              "for":["data","selected_reco"],
              "fluxnorm":false},
    "ThetamuDegrees":{"reco":"ThetamuDegrees",
                      "true":"TrueThetamuDegrees",
                      "name":"ThetamuDegrees",
                      "title":"theta_mu (degrees)",
                      "units":"Degree",
                      "nbins":20,
                      "min":0.,
                      "max":40.,
                      "fluxnorm":false},
    "ImprovedMichelCount":{"reco":"ImprovedNMichel",
                   "true":"TrueChargedPionCount",
                   "name":"ImprovedMichelCount",
                   "title":"Number of Michel Candidates (Improved)",
                   "units":"Michel Count",
                   "nbins":10,
                   "min":0.,
                   "max":10.,
                   "fluxnorm":false},
    "MichelCount":{"reco":"NMichel",
                   "true":"TrueChargedPionCount",
                   "name":"MichelCount",
                   "title":"Number of Michel Candidates (Old)",
                   "units":"Michel Count",
                   "nbins":10,
                   "min":0.,
                   "max":10.,
                   "fluxnorm":false},
    "FittedMichelCount":{"reco":"FittedNMichel",
                   "true":"TrueFittedNMichel",
                   "name":"FittedMichelCount",
                   "title":"Number of Michel Candidates (Fitted)",
                   "units":"Michel Count",
                   "nbins":10,
                   "min":0.,
                   "max":10.,
                   "fluxnorm":false},
    "PrimaryProtonScore":{"reco":"PrimaryProtonScore",
                          "true":"TruthHasSingleProton",
                          "name":"PrimaryProtonScore",
                          "title":"Proton Score of Primary non-Muon Track",
                          "units":"",
                          "nbins":20,
                          "min":0.,
                          "max":1.,
                          "fluxnorm":false},
    "AreClustsFoundAtPrimaryProtonEnd":{"reco":"AreClustsFoundAtPrimaryProtonEnd",
                                        "true":"TruthHasSingleProton",
                                        "name":"AreClustsFoundAtPrimaryProtonEnd",
                                        "title":"Are Clusters Found at End of Primary Proton Prong?",
                                        "units":"",
                                        "bins":[0.,1.,2.],
                                        "fluxnorm":false},
    "NumClustsPrimaryProtonEnd":{"reco":"NumClustsPrimaryProtonEnd",
                                 "true":"TruthHasSingleProton",
                                 "name":"NumClustsPrimaryProtonEnd",
                                 "title":"Number of Clusters Found at End of Primary Proton Prong",
                                 "units":"",
                                 "nbins":10,
                                 "min":0.,
                                 "max":15.,
                                 "fluxnorm":false},
    "PrimaryProtonTrackLength":{"reco":"PrimaryProtonTrackLength",
                                "true":"TrueZVertex",
                                "name":"PrimaryProtonTrackLength",
                                "title":"Primary Proton Track Length",
                                "units":"mm",
                                "nbins":25,
                                "min":0.,
                                "max":3000.,
                                "fluxnorm":false},
    "CalibEClustsPrimaryProtonEnd":{"reco":"CalibEClustsPrimaryProtonEnd",
                                    "true":"TrueRecoilEnergyGeV",
                                    "name":"CalibEClustsPrimaryProtonEnd",
                                    "title":"Calibrated Energy of Clusters Present at End of Primary Proton Track",
                                    "units":"MeV",
                                    "bins":[0.,5.,10.,15.,20.,40.,60.,80.,100.,200.,1000.],
                                    "fluxnorm":false},
    "VisEClustsPrimaryProtonEnd":{"reco":"VisEClustsPrimaryProtonEnd",
                                  "true":"TrueRecoilEnergyGeV",
                                  "name":"VisEClustsPrimaryProtonEnd",
                                  "title":"Visable Energy of Clusters Present at End of Primary Proton Track",
                                  "units":"MeV",
                                  "bins":[0.,5.,10.,15.,20.,40.,60.,80.,100.,200.,1000.],
                                  "fluxnorm":false},
    "PrimaryProtonTfromdEdx":{"reco":"PrimaryProtonTfromdEdx",
                              "true":"TrueRecoilEnergyGeV",
                              "name":"PrimaryProtonTfromdEdx",
                              "title":"Primary Proton KE Reconstructed from Track dE/dX",
                              "units":"MeV",
                              "nbins":100,
                              "min":0.,
                              "max":1000.,
                              "fluxnorm":false},
    "TotalPrimaryProtonEnergydEdxAndClusters":{"reco":"TotalPrimaryProtonEnergydEdxAndClusters",
                                               "true":"TrueRecoilEnergyGeV",
                                               "name":"TotalPrimaryProtonEnergydEdxAndClusters",
                                               "title":"Total Reco KE of Primary Proton from Track dE/dX and Clusters",
                                               "units":"MeV",
                                               "nbins":100,
                                               "min":0.,
                                               "max":1000.,
                                               "fluxnorm":false},
    "PrimaryProtonTrueKE":{"reco":"PrimaryProtonTrueKE",
                           "true":"TrueRecoilEnergyGeV",
                           "name":"PrimaryProtonTrueKE",
                           "title":"True KE of Primary Proton",
                           "units":"MeV",
                           "nbins":100,
                           "mins":0.,
                           "max":1000.,
                           "fluxnorm":false},
    "EnergyDiffTruedEdx":{"reco":"EnergyDiffTruedEdx",
                          "true":"TrueRecoilEnergyGeV",
                          "name":"EnergyDiffTruedEdx",
                          "title":"True KE of Primary Proton",
                          "units":"MeV",
                          "nbins":100,
                          "mins":-500..,
                          "max":500.,
                          "fluxnorm":false},
    "BlobCount":{"reco":"NBlobs",
                 "true":"TrueNeutralPionCount",
                 "name":"BlobCount",
                 "title":"Blob Count",
                 "units":"Blob Count",
                 "nbins":15,
                 "min":0.,
                 "max":15.,
                 "fluxnorm":false}
  }
}

