{
	"Mult2p":{
		"name":"Mult2p",
		"reco":"Mult2p",
		"phase_space":"phase_space",
		"signal":["qelike"],
		"background":["1neutralpion","1chargedpion","multipion","other"],
		"categories":{
			"qelike":{"for":["selected_reco","selected_truth","truth","response"]},
			"1neutralpion":{"for":["selected_reco"]},
			"1chargedpion":{"for":["selected_reco"]},
			"multipion":{"for":["selected_reco"]},
			"other":{"for":["selected_reco"]}
		}
	},
	"Mult1":{
		"name":"Mult1",
		"reco":"Mult1",
		"phase_space":"phase_space",
		"signal":["qelike"],
		"background":["1neutralpion","1chargedpion","multipion","other"],
		"categories":{
			"qelike":{"for":["selected_reco","selected_truth","truth","response"]},
			"1neutralpion":{"for":["selected_reco"]},
			"1chargedpion":{"for":["selected_reco"]},
			"multipion":{"for":["selected_reco"]},
			"other":{"for":["selected_reco"]}
		}
	},
	"MC_Mult1p_PrimaryIsProton":{
		"name":"MC_Mult1p_PrimaryIsProton",
		"reco":"MC_Mult1p_PrimaryIsProton",
		"phase_space":"phase_space",
		"signal":["qelike"],
		"background":["1neutralpion","1chargedpion","multipion","other"],
		"categories":{
			"qelike":{"for":["selected_reco"]},
			"1neutralpion":{"for":["selected_reco"]},
			"1chargedpion":{"for":["selected_reco"]},
			"multipion":{"for":["selected_reco"]},
			"other":{"for":["selected_reco"]}
		}
	},
	"MC_Mult1p_PrimaryIsNotProton":{
		"name":"MC_Mult1p_PrimaryIsNotProton",
		"reco":"MC_Mult1p_PrimaryIsNotProton",
		"phase_space":"phase_space",
		"signal":["qelike"],
		"background":["1neutralpion","1chargedpion","multipion","other"],
		"categories":{
			"qelike":{"for":["selected_reco"]},
			"1neutralpion":{"for":["selected_reco"]},
			"1chargedpion":{"for":["selected_reco"]},
			"multipion":{"for":["selected_reco"]},
			"other":{"for":["selected_reco"]}
		}
	},
	"Mult1p":{
		"name":"Mult1p",
		"reco":"Mult1p",
		"phase_space":"phase_space",
		"signal":["qelike"],
		"background":["1neutralpion","1chargedpion","multipion","other"],
		"categories":{
			"qelike":{"for":["selected_reco","selected_truth","truth","response"]},
			"1neutralpion":{"for":["selected_reco","selected_truth","truth"]},
			"1chargedpion":{"for":["selected_reco","selected_truth","truth"]},
			"multipion":{"for":["selected_reco","selected_truth","truth"]},
			"other":{"for":["selected_reco","selected_truth","truth"]}
		}
	},
	"_Mult1p":{
		"name":"Mult1p",
		"reco":"Mult1p",
		"phase_space":"phase_space",
		"signal":["qelike"],
		"background":["1neutralpion","1chargedpion","multipion","other"],
		"categories":{
			"qelike":{"for":["selected_reco"]},
			"1neutralpion":{"for":["selected_reco"]},
			"1chargedpion":{"for":["selected_reco"]},
			"multipion":{"for":["selected_reco"]},
			"other":{"for":["selected_reco"]}
		}
	},
	"Mult1TMVA035":{
		"name":"Mult1TMVA035",
		"reco":"Mult1TMVA035",
		"phase_space":"phase_space",
		"signal":["qelike"],
		"background":["1neutralpion","1chargedpion","multipion","other"],
		"categories":{
			"qelike":{"for":["selected_reco","selected_truth","truth","response"]},
			"1neutralpion":{"for":["selected_reco"]},
			"1chargedpion":{"for":["selected_reco"]},
			"multipion":{"for":["selected_reco"]},
			"other":{"for":["selected_reco"]}
		}
	},
	"Mult2pTMVA035":{
		"name":"Mult2pTMVA035",
		"reco":"Mult2pTMVA035",
		"phase_space":"phase_space",
		"signal":["qelike"],
		"background":["1neutralpion","1chargedpion","multipion","other"],
		"categories":{
			"qelike":{"for":["selected_reco","selected_truth","truth","response"]},
			"1neutralpion":{"for":["selected_reco"]},
			"1chargedpion":{"for":["selected_reco"]},
			"multipion":{"for":["selected_reco"]},
			"other":{"for":["selected_reco"]}
		}
	},
	"Mult1TMVA04":{
		"name":"Mult1TMVA04",
		"reco":"Mult1TMVA04",
		"phase_space":"phase_space",
		"signal":["qelike"],
		"background":["1neutralpion","1chargedpion","multipion","other"],
		"categories":{
			"qelike":{"for":["selected_reco","selected_truth","truth","response"]},
			"1neutralpion":{"for":["selected_reco"]},
			"1chargedpion":{"for":["selected_reco"]},
			"multipion":{"for":["selected_reco"]},
			"other":{"for":["selected_reco"]}
		}
	},
	"Mult2pTMVA04":{
		"name":"Mult2pTMVA04",
		"reco":"Mult2pTMVA04",
		"phase_space":"phase_space",
		"signal":["qelike"],
		"background":["1neutralpion","1chargedpion","multipion","other"],
		"categories":{
			"qelike":{"for":["selected_reco","selected_truth","truth","response"]},
			"1neutralpion":{"for":["selected_reco"]},
			"1chargedpion":{"for":["selected_reco"]},
			"multipion":{"for":["selected_reco"]},
			"other":{"for":["selected_reco"]}
		}
	},
	"Mult1p03":{
		"name":"Mult1p03",
		"reco":"Mult1p03",
		"phase_space":"phase_space",
		"signal":["qelike"],
		"background":["1neutralpion","1chargedpion","multipion","other"],
		"categories":{
			"qelike":{"for":["selected_reco","selected_truth","truth","response"]},
			"1neutralpion":{"for":["selected_reco","selected_truth","truth"]},
			"1chargedpion":{"for":["selected_reco","selected_truth","truth"]},
			"multipion":{"for":["selected_reco","selected_truth","truth"]},
			"other":{"for":["selected_reco","selected_truth","truth"]}
		}
	},
	"Mult1p04":{
		"name":"Mult1p04",
		"reco":"Mult1p04",
		"phase_space":"phase_space",
		"signal":["qelike"],
		"background":["1neutralpion","1chargedpion","multipion","other"],
		"categories":{
			"qelike":{"for":["selected_reco","selected_truth","truth","response"]},
			"1neutralpion":{"for":["selected_reco"]},
			"1chargedpion":{"for":["selected_reco"]},
			"multipion":{"for":["selected_reco"]},
			"other":{"for":["selected_reco"]}
		}
	}
}
